py_solanautil-2.1.7.dist-info/licenses/LICENSE
sol/__init__.py
sol/common_util.pyd
sol/common_util.so
sol/constants.pyd
sol/constants.so
sol/solana_instruction.pyd
sol/solana_instruction.so
sol/solana_struct.pyd
sol/solana_struct.so
sol/solana_transaction.pyd
sol/solana_transaction.so
sol/solana_util.pyd
sol/solana_util.so
py_solanautil-2.1.7.dist-info/METADATA
py_solanautil-2.1.7.dist-info/WHEEL
py_solanautil-2.1.7.dist-info/top_level.txt
py_solanautil-2.1.7.dist-info/RECORD
