Metadata-Version: 2.4
Name: py-solanautil
Version: 2.1.7
Summary: Python Solana Util for Humans
Home-page: 
Author: Gusarich Tede
Author-email: danielsedovzzz@gmail.com
Classifier: Programming Language :: Python :: 3
Classifier: Programming Language :: Python :: 3.11
Classifier: Programming Language :: Python :: 3.12
Classifier: Programming Language :: Python :: 3.13
Classifier: License :: OSI Approved :: MIT License
Classifier: Operating System :: OS Independent
Requires-Python: >=3.10
License-File: LICENSE
Requires-Dist: construct>=2.10.68
Requires-Dist: PyNaCl>=1.5.0
Requires-Dist: base58>=2.1.1
Requires-Dist: requests>=2.32.3
Requires-Dist: aiohttp>=3.11.12
Requires-Dist: pycryptodome
Dynamic: author
Dynamic: author-email
Dynamic: classifier
Dynamic: description
Dynamic: description-content-type
Dynamic: license-file
Dynamic: requires-dist
Dynamic: requires-python
Dynamic: summary
